src/CMakeLists.txt
src/docstringFormat.cpp
src/docstringFormat.hpp
src/extern/__init__.py
src/extern/pybind11/.appveyor.yml
src/extern/pybind11/.clang-format
src/extern/pybind11/.clang-tidy
src/extern/pybind11/.cmake-format.yaml
src/extern/pybind11/.codespell-ignore-lines
src/extern/pybind11/.gitattributes
src/extern/pybind11/.github/CODEOWNERS
src/extern/pybind11/.github/CONTRIBUTING.md
src/extern/pybind11/.github/ISSUE_TEMPLATE/bug-report.yml
src/extern/pybind11/.github/ISSUE_TEMPLATE/config.yml
src/extern/pybind11/.github/dependabot.yml
src/extern/pybind11/.github/labeler.yml
src/extern/pybind11/.github/labeler_merged.yml
src/extern/pybind11/.github/matchers/pylint.json
src/extern/pybind11/.github/pull_request_template.md
src/extern/pybind11/.github/workflows/ci.yml
src/extern/pybind11/.github/workflows/configure.yml
src/extern/pybind11/.github/workflows/format.yml
src/extern/pybind11/.github/workflows/labeler.yml
src/extern/pybind11/.github/workflows/pip.yml
src/extern/pybind11/.github/workflows/upstream.yml
src/extern/pybind11/.gitignore
src/extern/pybind11/.pre-commit-config.yaml
src/extern/pybind11/.readthedocs.yml
src/extern/pybind11/CMakeLists.txt
src/extern/pybind11/LICENSE
src/extern/pybind11/MANIFEST.in
src/extern/pybind11/README.rst
src/extern/pybind11/__init__.py
src/extern/pybind11/docs/Doxyfile
src/extern/pybind11/docs/_static/css/custom.css
src/extern/pybind11/docs/advanced/cast/chrono.rst
src/extern/pybind11/docs/advanced/cast/custom.rst
src/extern/pybind11/docs/advanced/cast/eigen.rst
src/extern/pybind11/docs/advanced/cast/functional.rst
src/extern/pybind11/docs/advanced/cast/index.rst
src/extern/pybind11/docs/advanced/cast/overview.rst
src/extern/pybind11/docs/advanced/cast/stl.rst
src/extern/pybind11/docs/advanced/cast/strings.rst
src/extern/pybind11/docs/advanced/classes.rst
src/extern/pybind11/docs/advanced/embedding.rst
src/extern/pybind11/docs/advanced/exceptions.rst
src/extern/pybind11/docs/advanced/functions.rst
docstring_generator_ext-0.0.26.dist-info/METADATA
docstring_generator_ext-0.0.26.dist-info/WHEEL
docstring_generator_ext-0.0.26.dist-info/RECORD
